digiglass
