Metadata-Version: 1.1
Name: digiglass
Version: 1.0.4
Summary: Search Digi-Key from your terminal
Home-page: https://github.com/mplewis/digiglass
Author: Matthew Lewis
Author-email: matt@mplewis.com
License: MIT
Platform: UNKNOWN
Classifier: Development Status :: 5 - Production/Stable
Classifier: License :: OSI Approved :: MIT License
Classifier: Operating System :: OS Independent
Classifier: Programming Language :: Python :: 3
Classifier: Programming Language :: Python :: 3.4
Classifier: Topic :: Internet :: WWW/HTTP :: Indexing/Search
